{"records":{"timestamp":"29-Aug-2025 15:30:00","underlyingValue":2328.6,"data":[{"expiryDates":"28-Oct-2025","CE":{"strikePrice":0,"expiryDate":null,"underlying":null,"identifier":null,"openInterest":0,"changeinOpenInterest":0,"pchangeinOpenInterest":0,"totalTradedVolume":0,"impliedVolatility":0,"lastPrice":0,"change":0,"totalBuyQuantity":0,"totalSellQuantity":0,"buyPrice1":0,"buyQuantity1":0,"sellPrice1":0,"sellQuantity1":0,"underlyingValue":0,"optionType":null,"pchange":0},"PE":{"strikePrice":1960,"expiryDate":"28-10-2025","underlying":"COLPAL","identifier":"OPTSTKCOLPAL28-10-2025PE1960.00","openInterest":0,"changeinOpenInterest":0,"pchangeinOpenInterest":0,"totalTradedVolume":0,"impliedVolatility":0,"lastPrice":0,"change":0,"totalBuyQuantity":17100,"totalSellQuantity":0,"buyPrice1":0.05,"buyQuantity1":17100,"sellPrice1":0,"sellQuantity1":0,"underlyingValue":2328.6,"optionType":null,"pchange":0},"strikePrice":1960},{"expiryDates":"28-Oct-2025","CE":{"strikePrice":2000,"expiryDate":"28-10-2025","underlying":"COLPAL","identifier":"OPTSTKCOLPAL28-10-2025CE2000.00","openInterest":0,"changeinOpenInterest":0,"pchangeinOpenInterest":0,"totalTradedVolume":0,"impliedVolatility":0,"lastPrice":0,"change":0,"totalBuyQuantity":6525,"totalSellQuantity":3150,"buyPrice1":344.05,"buyQuantity1":900,"sellPrice1":428.75,"sellQuantity1":900,"underlyingValue":2328.6,"optionType":null,"pchange":0},"PE":{"strikePrice":2000,"expiryDate":"28-10-2025","underlying":"COLPAL","identifier":"OPTSTKCOLPAL28-10-2025PE2000.00","openInterest":0,"changeinOpenInterest":0,"pchangeinOpenInterest":0,"totalTradedVolume":0,"impliedVolatility":0,"lastPrice":0,"change":0,"totalBuyQuantity":26100,"totalSellQuantity":0,"buyPrice1":1.25,"buyQuantity1":450,"sellPrice1":0,"sellQuantity1":0,"underlyingValue":2328.6,"optionType":null,"pchange":0},"strikePrice":2000},{"expiryDates":"28-Oct-2025","CE":{"strikePrice":0,"expiryDate":null,"underlying":null,"identifier":null,"openInterest":0,"changeinOpenInterest":0,"pchangeinOpenInterest":0,"totalTradedVolume":0,"impliedVolatility":0,"lastPrice":0,"change":0,"totalBuyQuantity":0,"totalSellQuantity":0,"buyPrice1":0,"buyQuantity1":0,"sellPrice1":0,"sellQuantity1":0,"underlyingValue":0,"optionType":null,"pchange":0},"PE":{"strikePrice":2020,"expiryDate":"28-10-2025","underlying":"COLPAL","identifier":"OPTSTKCOLPAL28-10-2025PE2020.00","openInterest":0,"changeinOpenInterest":0,"pchangeinOpenInterest":0,"totalTradedVolume":0,"impliedVolatility":0,"lastPrice":0,"change":0,"totalBuyQuantity":25650,"totalSellQuantity":0,"buyPrice1":0.05,"buyQuantity1":25650,"sellPrice1":0,"sellQuantity1":0,"underlyingValue":2328.6,"optionType":null,"pchange":0},"strikePrice":2020},{"expiryDates":"28-Oct-2025","CE":{"strikePrice":2040,"expiryDate":"28-10-2025","underlying":"COLPAL","identifier":"OPTSTKCOLPAL28-10-2025CE2040.00","openInterest":0,"changeinOpenInterest":0,"pchangeinOpenInterest":0,"totalTradedVolume":0,"impliedVolatility":0,"lastPrice":0,"change":0,"totalBuyQuantity":6525,"totalSellQuantity":3150,"buyPrice1":304.55,"buyQuantity1":900,"sellPrice1":389.25,"sellQuantity1":900,"underlyingValue":2328.6,"optionType":null,"pchange":0},"PE":{"strikePrice":2040,"expiryDate":"28-10-2025","underlying":"COLPAL","identifier":"OPTSTKCOLPAL28-10-2025PE2040.00","openInterest":0,"changeinOpenInterest":0,"pchangeinOpenInterest":0,"totalTradedVolume":0,"impliedVolatility":0,"lastPrice":0,"change":0,"totalBuyQuantity":0,"totalSellQuantity":0,"buyPrice1":0,"buyQuantity1":0,"sellPrice1":0,"sellQuantity1":0,"underlyingValue":2328.6,"optionType":null,"pchange":0},"strikePrice":2040},{"expiryDates":"28-Oct-2025","CE":{"strikePrice":2080,"expiryDate":"28-10-2025","underlying":"COLPAL","identifier":"OPTSTKCOLPAL28-10-2025CE2080.00","openInterest":0,"changeinOpenInterest":0,"pchangeinOpenInterest":0,"totalTradedVolume":0,"impliedVolatility":0,"lastPrice":0,"change":0,"totalBuyQuantity":6525,"totalSellQuantity":3150,"buyPrice1":265.05,"buyQuantity1":900,"sellPrice1":349.75,"sellQuantity1":900,"underlyingValue":2328.6,"optionType":null,"pchange":0},"PE":{"strikePrice":2080,"expiryDate":"28-10-2025","underlying":"COLPAL","identifier":"OPTSTKCOLPAL28-10-2025PE2080.00","openInterest":0,"changeinOpenInterest":0,"pchangeinOpenInterest":0,"totalTradedVolume":0,"impliedVolatility":0,"lastPrice":0,"change":0,"totalBuyQuantity":0,"totalSellQuantity":0,"buyPrice1":0,"buyQuantity1":0,"sellPrice1":0,"sellQuantity1":0,"underlyingValue":2328.6,"optionType":null,"pchange":0},"strikePrice":2080},{"expiryDates":"28-Oct-2025","CE":{"strikePrice":2120,"expiryDate":"28-10-2025","underlying":"COLPAL","identifier":"OPTSTKCOLPAL28-10-2025CE2120.00","openInterest":0,"changeinOpenInterest":0,"pchangeinOpenInterest":0,"totalTradedVolume":0,"impliedVolatility":0,"lastPrice":0,"change":0,"totalBuyQuantity":6525,"totalSellQuantity":3150,"buyPrice1":225.55,"buyQuantity1":900,"sellPrice1":310.25,"sellQuantity1":900,"underlyingValue":2328.6,"optionType":null,"pchange":0},"PE":{"strikePrice":2120,"expiryDate":"28-10-2025","underlying":"COLPAL","identifier":"OPTSTKCOLPAL28-10-2025PE2120.00","openInterest":0,"changeinOpenInterest":0,"pchangeinOpenInterest":0,"totalTradedVolume":0,"impliedVolatility":0,"lastPrice":0,"change":0,"totalBuyQuantity":0,"totalSellQuantity":0,"buyPrice1":0,"buyQuantity1":0,"sellPrice1":0,"sellQuantity1":0,"underlyingValue":2328.6,"optionType":null,"pchange":0},"strikePrice":2120},{"expiryDates":"28-Oct-2025","CE":{"strikePrice":2160,"expiryDate":"28-10-2025","underlying":"COLPAL","identifier":"OPTSTKCOLPAL28-10-2025CE2160.00","openInterest":0,"changeinOpenInterest":0,"pchangeinOpenInterest":0,"totalTradedVolume":0,"impliedVolatility":0,"lastPrice":0,"change":0,"totalBuyQuantity":6525,"totalSellQuantity":3150,"buyPrice1":186.05,"buyQuantity1":900,"sellPrice1":270.75,"sellQuantity1":900,"underlyingValue":2328.6,"optionType":null,"pchange":0},"PE":{"strikePrice":2160,"expiryDate":"28-10-2025","underlying":"COLPAL","identifier":"OPTSTKCOLPAL28-10-2025PE2160.00","openInterest":0,"changeinOpenInterest":0,"pchangeinOpenInterest":0,"totalTradedVolume":0,"impliedVolatility":0,"lastPrice":0,"change":0,"totalBuyQuantity":0,"totalSellQuantity":6525,"buyPrice1":0,"buyQuantity1":0,"sellPrice1":68.25,"sellQuantity1":900,"underlyingValue":2328.6,"optionType":null,"pchange":0},"strikePrice":2160},{"expiryDates":"28-Oct-2025","CE":{"strikePrice":2200,"expiryDate":"28-10-2025","underlying":"COLPAL","identifier":"OPTSTKCOLPAL28-10-2025CE2200.00","openInterest":0,"changeinOpenInterest":0,"pchangeinOpenInterest":0,"totalTradedVolume":0,"impliedVolatility":0,"lastPrice":0,"change":0,"totalBuyQuantity":6525,"totalSellQuantity":900,"buyPrice1":147.55,"buyQuantity1":900,"sellPrice1":228.55,"sellQuantity1":900,"underlyingValue":2328.6,"optionType":null,"pchange":0},"PE":{"strikePrice":2200,"expiryDate":"28-10-2025","underlying":"COLPAL","identifier":"OPTSTKCOLPAL28-10-2025PE2200.00","openInterest":0,"changeinOpenInterest":0,"pchangeinOpenInterest":0,"totalTradedVolume":0,"impliedVolatility":0,"lastPrice":0,"change":0,"totalBuyQuantity":450,"totalSellQuantity":6525,"buyPrice1":15.05,"buyQuantity1":450,"sellPrice1":68.6,"sellQuantity1":900,"underlyingValue":2328.6,"optionType":null,"pchange":0},"strikePrice":2200},{"expiryDates":"28-Oct-2025","CE":{"strikePrice":2240,"expiryDate":"28-10-2025","underlying":"COLPAL","identifier":"OPTSTKCOLPAL28-10-2025CE2240.00","openInterest":0,"changeinOpenInterest":0,"pchangeinOpenInterest":0,"totalTradedVolume":0,"impliedVolatility":0,"lastPrice":0,"change":0,"totalBuyQuantity":6525,"totalSellQuantity":3150,"buyPrice1":107.65,"buyQuantity1":900,"sellPrice1":189.55,"sellQuantity1":900,"underlyingValue":2328.6,"optionType":null,"pchange":0},"PE":{"strikePrice":2240,"expiryDate":"28-10-2025","underlying":"COLPAL","identifier":"OPTSTKCOLPAL28-10-2025PE2240.00","openInterest":0,"changeinOpenInterest":0,"pchangeinOpenInterest":0,"totalTradedVolume":0,"impliedVolatility":0,"lastPrice":0,"change":0,"totalBuyQuantity":0,"totalSellQuantity":6750,"buyPrice1":0,"buyQuantity1":0,"sellPrice1":60,"sellQuantity1":225,"underlyingValue":2328.6,"optionType":null,"pchange":0},"strikePrice":2240},{"expiryDates":"28-Oct-2025","CE":{"strikePrice":2280,"expiryDate":"28-10-2025","underlying":"COLPAL","identifier":"OPTSTKCOLPAL28-10-2025CE2280.00","openInterest":0,"changeinOpenInterest":0,"pchangeinOpenInterest":0,"totalTradedVolume":0,"impliedVolatility":0,"lastPrice":0,"change":0,"totalBuyQuantity":6525,"totalSellQuantity":6525,"buyPrice1":67.55,"buyQuantity1":900,"sellPrice1":161.6,"sellQuantity1":1125,"underlyingValue":2328.6,"optionType":null,"pchange":0},"PE":{"strikePrice":2280,"expiryDate":"28-10-2025","underlying":"COLPAL","identifier":"OPTSTKCOLPAL28-10-2025PE2280.00","openInterest":0,"changeinOpenInterest":0,"pchangeinOpenInterest":0,"totalTradedVolume":0,"impliedVolatility":0,"lastPrice":0,"change":0,"totalBuyQuantity":225,"totalSellQuantity":6525,"buyPrice1":35.05,"buyQuantity1":225,"sellPrice1":76.45,"sellQuantity1":900,"underlyingValue":2328.6,"optionType":null,"pchange":0},"strikePrice":2280},{"expiryDates":"28-Oct-2025","CE":{"strikePrice":2300,"expiryDate":"28-10-2025","underlying":"COLPAL","identifier":"OPTSTKCOLPAL28-10-2025CE2300.00","openInterest":0,"changeinOpenInterest":0,"pchangeinOpenInterest":0,"totalTradedVolume":0,"impliedVolatility":0,"lastPrice":0,"change":0,"totalBuyQuantity":0,"totalSellQuantity":0,"buyPrice1":0,"buyQuantity1":0,"sellPrice1":0,"sellQuantity1":0,"underlyingValue":2328.6,"optionType":null,"pchange":0},"PE":{"strikePrice":2300,"expiryDate":"28-10-2025","underlying":"COLPAL","identifier":"OPTSTKCOLPAL28-10-2025PE2300.00","openInterest":0,"changeinOpenInterest":0,"pchangeinOpenInterest":0,"totalTradedVolume":0,"impliedVolatility":0,"lastPrice":0,"change":0,"totalBuyQuantity":225,"totalSellQuantity":450,"buyPrice1":39.15,"buyQuantity1":225,"sellPrice1":67.95,"sellQuantity1":225,"underlyingValue":2328.6,"optionType":null,"pchange":0},"strikePrice":2300},{"expiryDates":"28-Oct-2025","CE":{"strikePrice":2320,"expiryDate":"28-10-2025","underlying":"COLPAL","identifier":"OPTSTKCOLPAL28-10-2025CE2320.00","openInterest":0,"changeinOpenInterest":0,"pchangeinOpenInterest":0,"totalTradedVolume":0,"impliedVolatility":0,"lastPrice":0,"change":0,"totalBuyQuantity":0,"totalSellQuantity":6750,"buyPrice1":0,"buyQuantity1":0,"sellPrice1":160.1,"sellQuantity1":225,"underlyingValue":2328.6,"optionType":null,"pchange":0},"PE":{"strikePrice":2320,"expiryDate":"28-10-2025","underlying":"COLPAL","identifier":"OPTSTKCOLPAL28-10-2025PE2320.00","openInterest":0,"changeinOpenInterest":0,"pchangeinOpenInterest":0,"totalTradedVolume":0,"impliedVolatility":0,"lastPrice":0,"change":0,"totalBuyQuantity":225,"totalSellQuantity":6525,"buyPrice1":46.65,"buyQuantity1":225,"sellPrice1":134.1,"sellQuantity1":900,"underlyingValue":2328.6,"optionType":null,"pchange":0},"strikePrice":2320},{"expiryDates":"28-Oct-2025","CE":{"strikePrice":2340,"expiryDate":"28-10-2025","underlying":"COLPAL","identifier":"OPTSTKCOLPAL28-10-2025CE2340.00","openInterest":0,"changeinOpenInterest":0,"pchangeinOpenInterest":0,"totalTradedVolume":0,"impliedVolatility":0,"lastPrice":0,"change":0,"totalBuyQuantity":0,"totalSellQuantity":225,"buyPrice1":0,"buyQuantity1":0,"sellPrice1":123.15,"sellQuantity1":225,"underlyingValue":2328.6,"optionType":null,"pchange":0},"PE":{"strikePrice":0,"expiryDate":null,"underlying":null,"identifier":null,"openInterest":0,"changeinOpenInterest":0,"pchangeinOpenInterest":0,"totalTradedVolume":0,"impliedVolatility":0,"lastPrice":0,"change":0,"totalBuyQuantity":0,"totalSellQuantity":0,"buyPrice1":0,"buyQuantity1":0,"sellPrice1":0,"sellQuantity1":0,"underlyingValue":0,"optionType":null,"pchange":0},"strikePrice":2340},{"expiryDates":"28-Oct-2025","CE":{"strikePrice":2360,"expiryDate":"28-10-2025","underlying":"COLPAL","identifier":"OPTSTKCOLPAL28-10-2025CE2360.00","openInterest":0,"changeinOpenInterest":0,"pchangeinOpenInterest":0,"totalTradedVolume":0,"impliedVolatility":0,"lastPrice":0,"change":0,"totalBuyQuantity":0,"totalSellQuantity":3375,"buyPrice1":0,"buyQuantity1":0,"sellPrice1":109.65,"sellQuantity1":225,"underlyingValue":2328.6,"optionType":null,"pchange":0},"PE":{"strikePrice":2360,"expiryDate":"28-10-2025","underlying":"COLPAL","identifier":"OPTSTKCOLPAL28-10-2025PE2360.00","openInterest":0,"changeinOpenInterest":0,"pchangeinOpenInterest":0,"totalTradedVolume":0,"impliedVolatility":0,"lastPrice":0,"change":0,"totalBuyQuantity":0,"totalSellQuantity":6525,"buyPrice1":0,"buyQuantity1":0,"sellPrice1":134.05,"sellQuantity1":900,"underlyingValue":2328.6,"optionType":null,"pchange":0},"strikePrice":2360},{"expiryDates":"28-Oct-2025","CE":{"strikePrice":2380,"expiryDate":"28-10-2025","underlying":"COLPAL","identifier":"OPTSTKCOLPAL28-10-2025CE2380.00","openInterest":0,"changeinOpenInterest":0,"pchangeinOpenInterest":0,"totalTradedVolume":0,"impliedVolatility":0,"lastPrice":0,"change":0,"totalBuyQuantity":0,"totalSellQuantity":225,"buyPrice1":0,"buyQuantity1":0,"sellPrice1":103.95,"sellQuantity1":225,"underlyingValue":2328.6,"optionType":null,"pchange":0},"PE":{"strikePrice":0,"expiryDate":null,"underlying":null,"identifier":null,"openInterest":0,"changeinOpenInterest":0,"pchangeinOpenInterest":0,"totalTradedVolume":0,"impliedVolatility":0,"lastPrice":0,"change":0,"totalBuyQuantity":0,"totalSellQuantity":0,"buyPrice1":0,"buyQuantity1":0,"sellPrice1":0,"sellQuantity1":0,"underlyingValue":0,"optionType":null,"pchange":0},"strikePrice":2380},{"expiryDates":"28-Oct-2025","CE":{"strikePrice":2400,"expiryDate":"28-10-2025","underlying":"COLPAL","identifier":"OPTSTKCOLPAL28-10-2025CE2400.00","openInterest":2,"changeinOpenInterest":2,"pchangeinOpenInterest":0,"totalTradedVolume":3,"impliedVolatility":21.97,"lastPrice":68.15,"change":-11.85,"totalBuyQuantity":225,"totalSellQuantity":7425,"buyPrice1":25,"buyQuantity1":225,"sellPrice1":70.7,"sellQuantity1":225,"underlyingValue":2328.6,"optionType":null,"pchange":-14.8125},"PE":{"strikePrice":2400,"expiryDate":"28-10-2025","underlying":"COLPAL","identifier":"OPTSTKCOLPAL28-10-2025PE2400.00","openInterest":0,"changeinOpenInterest":0,"pchangeinOpenInterest":0,"totalTradedVolume":0,"impliedVolatility":0,"lastPrice":0,"change":0,"totalBuyQuantity":0,"totalSellQuantity":6525,"buyPrice1":0,"buyQuantity1":0,"sellPrice1":125.85,"sellQuantity1":2250,"underlyingValue":2328.6,"optionType":null,"pchange":0},"strikePrice":2400},{"expiryDates":"28-Oct-2025","CE":{"strikePrice":2420,"expiryDate":"28-10-2025","underlying":"COLPAL","identifier":"OPTSTKCOLPAL28-10-2025CE2420.00","openInterest":0,"changeinOpenInterest":0,"pchangeinOpenInterest":0,"totalTradedVolume":0,"impliedVolatility":0,"lastPrice":0,"change":0,"totalBuyQuantity":0,"totalSellQuantity":225,"buyPrice1":0,"buyQuantity1":0,"sellPrice1":82.85,"sellQuantity1":225,"underlyingValue":2328.6,"optionType":null,"pchange":0},"PE":{"strikePrice":0,"expiryDate":null,"underlying":null,"identifier":null,"openInterest":0,"changeinOpenInterest":0,"pchangeinOpenInterest":0,"totalTradedVolume":0,"impliedVolatility":0,"lastPrice":0,"change":0,"totalBuyQuantity":0,"totalSellQuantity":0,"buyPrice1":0,"buyQuantity1":0,"sellPrice1":0,"sellQuantity1":0,"underlyingValue":0,"optionType":null,"pchange":0},"strikePrice":2420},{"expiryDates":"28-Oct-2025","CE":{"strikePrice":2440,"expiryDate":"28-10-2025","underlying":"COLPAL","identifier":"OPTSTKCOLPAL28-10-2025CE2440.00","openInterest":0,"changeinOpenInterest":0,"pchangeinOpenInterest":0,"totalTradedVolume":0,"impliedVolatility":0,"lastPrice":0,"change":0,"totalBuyQuantity":0,"totalSellQuantity":6750,"buyPrice1":0,"buyQuantity1":0,"sellPrice1":75.05,"sellQuantity1":225,"underlyingValue":2328.6,"optionType":null,"pchange":0},"PE":{"strikePrice":2440,"expiryDate":"28-10-2025","underlying":"COLPAL","identifier":"OPTSTKCOLPAL28-10-2025PE2440.00","openInterest":0,"changeinOpenInterest":0,"pchangeinOpenInterest":0,"totalTradedVolume":0,"impliedVolatility":0,"lastPrice":0,"change":0,"totalBuyQuantity":0,"totalSellQuantity":6525,"buyPrice1":0,"buyQuantity1":0,"sellPrice1":171.4,"sellQuantity1":900,"underlyingValue":2328.6,"optionType":null,"pchange":0},"strikePrice":2440},{"expiryDates":"28-Oct-2025","CE":{"strikePrice":2460,"expiryDate":"28-10-2025","underlying":"COLPAL","identifier":"OPTSTKCOLPAL28-10-2025CE2460.00","openInterest":0,"changeinOpenInterest":0,"pchangeinOpenInterest":0,"totalTradedVolume":0,"impliedVolatility":0,"lastPrice":0,"change":0,"totalBuyQuantity":0,"totalSellQuantity":225,"buyPrice1":0,"buyQuantity1":0,"sellPrice1":71.55,"sellQuantity1":225,"underlyingValue":2328.6,"optionType":null,"pchange":0},"PE":{"strikePrice":0,"expiryDate":null,"underlying":null,"identifier":null,"openInterest":0,"changeinOpenInterest":0,"pchangeinOpenInterest":0,"totalTradedVolume":0,"impliedVolatility":0,"lastPrice":0,"change":0,"totalBuyQuantity":0,"totalSellQuantity":0,"buyPrice1":0,"buyQuantity1":0,"sellPrice1":0,"sellQuantity1":0,"underlyingValue":0,"optionType":null,"pchange":0},"strikePrice":2460},{"expiryDates":"28-Oct-2025","CE":{"strikePrice":2480,"expiryDate":"28-10-2025","underlying":"COLPAL","identifier":"OPTSTKCOLPAL28-10-2025CE2480.00","openInterest":0,"changeinOpenInterest":0,"pchangeinOpenInterest":0,"totalTradedVolume":0,"impliedVolatility":0,"lastPrice":0,"change":0,"totalBuyQuantity":0,"totalSellQuantity":3375,"buyPrice1":0,"buyQuantity1":0,"sellPrice1":68.4,"sellQuantity1":225,"underlyingValue":2328.6,"optionType":null,"pchange":0},"PE":{"strikePrice":2480,"expiryDate":"28-10-2025","underlying":"COLPAL","identifier":"OPTSTKCOLPAL28-10-2025PE2480.00","openInterest":0,"changeinOpenInterest":0,"pchangeinOpenInterest":0,"totalTradedVolume":0,"impliedVolatility":0,"lastPrice":0,"change":0,"totalBuyQuantity":3150,"totalSellQuantity":6525,"buyPrice1":106.15,"buyQuantity1":900,"sellPrice1":213.5,"sellQuantity1":2250,"underlyingValue":2328.6,"optionType":null,"pchange":0},"strikePrice":2480},{"expiryDates":"28-Oct-2025","CE":{"strikePrice":2500,"expiryDate":"28-10-2025","underlying":"COLPAL","identifier":"OPTSTKCOLPAL28-10-2025CE2500.00","openInterest":0,"changeinOpenInterest":0,"pchangeinOpenInterest":0,"totalTradedVolume":0,"impliedVolatility":0,"lastPrice":0,"change":0,"totalBuyQuantity":225,"totalSellQuantity":225,"buyPrice1":12,"buyQuantity1":225,"sellPrice1":65.25,"sellQuantity1":225,"underlyingValue":2328.6,"optionType":null,"pchange":0},"PE":{"strikePrice":0,"expiryDate":null,"underlying":null,"identifier":null,"openInterest":0,"changeinOpenInterest":0,"pchangeinOpenInterest":0,"totalTradedVolume":0,"impliedVolatility":0,"lastPrice":0,"change":0,"totalBuyQuantity":0,"totalSellQuantity":0,"buyPrice1":0,"buyQuantity1":0,"sellPrice1":0,"sellQuantity1":0,"underlyingValue":0,"optionType":null,"pchange":0},"strikePrice":2500},{"expiryDates":"28-Oct-2025","CE":{"strikePrice":2520,"expiryDate":"28-10-2025","underlying":"COLPAL","identifier":"OPTSTKCOLPAL28-10-2025CE2520.00","openInterest":0,"changeinOpenInterest":0,"pchangeinOpenInterest":0,"totalTradedVolume":0,"impliedVolatility":0,"lastPrice":0,"change":0,"totalBuyQuantity":0,"totalSellQuantity":3375,"buyPrice1":0,"buyQuantity1":0,"sellPrice1":73.75,"sellQuantity1":225,"underlyingValue":2328.6,"optionType":null,"pchange":0},"PE":{"strikePrice":2520,"expiryDate":"28-10-2025","underlying":"COLPAL","identifier":"OPTSTKCOLPAL28-10-2025PE2520.00","openInterest":0,"changeinOpenInterest":0,"pchangeinOpenInterest":0,"totalTradedVolume":0,"impliedVolatility":0,"lastPrice":0,"change":0,"totalBuyQuantity":3150,"totalSellQuantity":6525,"buyPrice1":144.8,"buyQuantity1":900,"sellPrice1":246.65,"sellQuantity1":900,"underlyingValue":2328.6,"optionType":null,"pchange":0},"strikePrice":2520},{"expiryDates":"28-Oct-2025","CE":{"strikePrice":2560,"expiryDate":"28-10-2025","underlying":"COLPAL","identifier":"OPTSTKCOLPAL28-10-2025CE2560.00","openInterest":0,"changeinOpenInterest":0,"pchangeinOpenInterest":0,"totalTradedVolume":0,"impliedVolatility":0,"lastPrice":0,"change":0,"totalBuyQuantity":0,"totalSellQuantity":225,"buyPrice1":0,"buyQuantity1":0,"sellPrice1":65.75,"sellQuantity1":225,"underlyingValue":2328.6,"optionType":null,"pchange":0},"PE":{"strikePrice":2560,"expiryDate":"28-10-2025","underlying":"COLPAL","identifier":"OPTSTKCOLPAL28-10-2025PE2560.00","openInterest":0,"changeinOpenInterest":0,"pchangeinOpenInterest":0,"totalTradedVolume":0,"impliedVolatility":0,"lastPrice":0,"change":0,"totalBuyQuantity":3150,"totalSellQuantity":6525,"buyPrice1":184.3,"buyQuantity1":900,"sellPrice1":286.45,"sellQuantity1":900,"underlyingValue":2328.6,"optionType":null,"pchange":0},"strikePrice":2560},{"expiryDates":"28-Oct-2025","CE":{"strikePrice":2600,"expiryDate":"28-10-2025","underlying":"COLPAL","identifier":"OPTSTKCOLPAL28-10-2025CE2600.00","openInterest":0,"changeinOpenInterest":0,"pchangeinOpenInterest":0,"totalTradedVolume":0,"impliedVolatility":0,"lastPrice":0,"change":0,"totalBuyQuantity":18450,"totalSellQuantity":0,"buyPrice1":0.5,"buyQuantity1":1350,"sellPrice1":0,"sellQuantity1":0,"underlyingValue":2328.6,"optionType":null,"pchange":0},"PE":{"strikePrice":0,"expiryDate":null,"underlying":null,"identifier":null,"openInterest":0,"changeinOpenInterest":0,"pchangeinOpenInterest":0,"totalTradedVolume":0,"impliedVolatility":0,"lastPrice":0,"change":0,"totalBuyQuantity":0,"totalSellQuantity":0,"buyPrice1":0,"buyQuantity1":0,"sellPrice1":0,"sellQuantity1":0,"underlyingValue":0,"optionType":null,"pchange":0},"strikePrice":2600},{"expiryDates":"28-Oct-2025","CE":{"strikePrice":2640,"expiryDate":"28-10-2025","underlying":"COLPAL","identifier":"OPTSTKCOLPAL28-10-2025CE2640.00","openInterest":0,"changeinOpenInterest":0,"pchangeinOpenInterest":0,"totalTradedVolume":0,"impliedVolatility":0,"lastPrice":0,"change":0,"totalBuyQuantity":17100,"totalSellQuantity":0,"buyPrice1":0.1,"buyQuantity1":17100,"sellPrice1":0,"sellQuantity1":0,"underlyingValue":2328.6,"optionType":null,"pchange":0},"PE":{"strikePrice":0,"expiryDate":null,"underlying":null,"identifier":null,"openInterest":0,"changeinOpenInterest":0,"pchangeinOpenInterest":0,"totalTradedVolume":0,"impliedVolatility":0,"lastPrice":0,"change":0,"totalBuyQuantity":0,"totalSellQuantity":0,"buyPrice1":0,"buyQuantity1":0,"sellPrice1":0,"sellQuantity1":0,"underlyingValue":0,"optionType":null,"pchange":0},"strikePrice":2640}],"expiryDates":["30-Sep-2025","28-Oct-2025","25-Nov-2025"],"strikePrices":["1080","1120","1160","1200","1240","1280","1320","1360","1400","1440","1460","1480","1500","1520","1540","1560","1580","1600","1620","1640","1660","1680","1700","1720","1740","1760","1780","1800","1820","1840","1860","1880","1900","1920","1940","1960","1980","2000","2020","2040","2060","2080","2100","2120","2140","2160","2180","2200","2220","2240","2260","2280","2300","2320","2340","2360","2380","2400","2420","2440","2460","2480","2500","2520","2540","2560","2580","2600","2620","2640","2660","2680","2700","2720","2740","2760","2780","2800","2820","2840","2860","2880","2900","2920","2940","2960","2980","3000","3020","3040","3060","3080","3120","3160","3200","3240","3280","3320","3360","3400","3440"]},"filtered":{"data":[{"expiryDates":"28-Oct-2025","CE":{"strikePrice":0,"expiryDate":null,"underlying":null,"identifier":null,"openInterest":0,"changeinOpenInterest":0,"pchangeinOpenInterest":0,"totalTradedVolume":0,"impliedVolatility":0,"lastPrice":0,"change":0,"totalBuyQuantity":0,"totalSellQuantity":0,"buyPrice1":0,"buyQuantity1":0,"sellPrice1":0,"sellQuantity1":0,"underlyingValue":0,"optionType":null,"pchange":0},"PE":{"strikePrice":1960,"expiryDate":"28-10-2025","underlying":"COLPAL","identifier":"OPTSTKCOLPAL28-10-2025PE1960.00","openInterest":0,"changeinOpenInterest":0,"pchangeinOpenInterest":0,"totalTradedVolume":0,"impliedVolatility":0,"lastPrice":0,"change":0,"totalBuyQuantity":17100,"totalSellQuantity":0,"buyPrice1":0.05,"buyQuantity1":17100,"sellPrice1":0,"sellQuantity1":0,"underlyingValue":2328.6,"optionType":null,"pchange":0},"strikePrice":1960},{"expiryDates":"28-Oct-2025","CE":{"strikePrice":2000,"expiryDate":"28-10-2025","underlying":"COLPAL","identifier":"OPTSTKCOLPAL28-10-2025CE2000.00","openInterest":0,"changeinOpenInterest":0,"pchangeinOpenInterest":0,"totalTradedVolume":0,"impliedVolatility":0,"lastPrice":0,"change":0,"totalBuyQuantity":6525,"totalSellQuantity":3150,"buyPrice1":344.05,"buyQuantity1":900,"sellPrice1":428.75,"sellQuantity1":900,"underlyingValue":2328.6,"optionType":null,"pchange":0},"PE":{"strikePrice":2000,"expiryDate":"28-10-2025","underlying":"COLPAL","identifier":"OPTSTKCOLPAL28-10-2025PE2000.00","openInterest":0,"changeinOpenInterest":0,"pchangeinOpenInterest":0,"totalTradedVolume":0,"impliedVolatility":0,"lastPrice":0,"change":0,"totalBuyQuantity":26100,"totalSellQuantity":0,"buyPrice1":1.25,"buyQuantity1":450,"sellPrice1":0,"sellQuantity1":0,"underlyingValue":2328.6,"optionType":null,"pchange":0},"strikePrice":2000},{"expiryDates":"28-Oct-2025","CE":{"strikePrice":0,"expiryDate":null,"underlying":null,"identifier":null,"openInterest":0,"changeinOpenInterest":0,"pchangeinOpenInterest":0,"totalTradedVolume":0,"impliedVolatility":0,"lastPrice":0,"change":0,"totalBuyQuantity":0,"totalSellQuantity":0,"buyPrice1":0,"buyQuantity1":0,"sellPrice1":0,"sellQuantity1":0,"underlyingValue":0,"optionType":null,"pchange":0},"PE":{"strikePrice":2020,"expiryDate":"28-10-2025","underlying":"COLPAL","identifier":"OPTSTKCOLPAL28-10-2025PE2020.00","openInterest":0,"changeinOpenInterest":0,"pchangeinOpenInterest":0,"totalTradedVolume":0,"impliedVolatility":0,"lastPrice":0,"change":0,"totalBuyQuantity":25650,"totalSellQuantity":0,"buyPrice1":0.05,"buyQuantity1":25650,"sellPrice1":0,"sellQuantity1":0,"underlyingValue":2328.6,"optionType":null,"pchange":0},"strikePrice":2020},{"expiryDates":"28-Oct-2025","CE":{"strikePrice":2040,"expiryDate":"28-10-2025","underlying":"COLPAL","identifier":"OPTSTKCOLPAL28-10-2025CE2040.00","openInterest":0,"changeinOpenInterest":0,"pchangeinOpenInterest":0,"totalTradedVolume":0,"impliedVolatility":0,"lastPrice":0,"change":0,"totalBuyQuantity":6525,"totalSellQuantity":3150,"buyPrice1":304.55,"buyQuantity1":900,"sellPrice1":389.25,"sellQuantity1":900,"underlyingValue":2328.6,"optionType":null,"pchange":0},"PE":{"strikePrice":2040,"expiryDate":"28-10-2025","underlying":"COLPAL","identifier":"OPTSTKCOLPAL28-10-2025PE2040.00","openInterest":0,"changeinOpenInterest":0,"pchangeinOpenInterest":0,"totalTradedVolume":0,"impliedVolatility":0,"lastPrice":0,"change":0,"totalBuyQuantity":0,"totalSellQuantity":0,"buyPrice1":0,"buyQuantity1":0,"sellPrice1":0,"sellQuantity1":0,"underlyingValue":2328.6,"optionType":null,"pchange":0},"strikePrice":2040},{"expiryDates":"28-Oct-2025","CE":{"strikePrice":2080,"expiryDate":"28-10-2025","underlying":"COLPAL","identifier":"OPTSTKCOLPAL28-10-2025CE2080.00","openInterest":0,"changeinOpenInterest":0,"pchangeinOpenInterest":0,"totalTradedVolume":0,"impliedVolatility":0,"lastPrice":0,"change":0,"totalBuyQuantity":6525,"totalSellQuantity":3150,"buyPrice1":265.05,"buyQuantity1":900,"sellPrice1":349.75,"sellQuantity1":900,"underlyingValue":2328.6,"optionType":null,"pchange":0},"PE":{"strikePrice":2080,"expiryDate":"28-10-2025","underlying":"COLPAL","identifier":"OPTSTKCOLPAL28-10-2025PE2080.00","openInterest":0,"changeinOpenInterest":0,"pchangeinOpenInterest":0,"totalTradedVolume":0,"impliedVolatility":0,"lastPrice":0,"change":0,"totalBuyQuantity":0,"totalSellQuantity":0,"buyPrice1":0,"buyQuantity1":0,"sellPrice1":0,"sellQuantity1":0,"underlyingValue":2328.6,"optionType":null,"pchange":0},"strikePrice":2080},{"expiryDates":"28-Oct-2025","CE":{"strikePrice":2120,"expiryDate":"28-10-2025","underlying":"COLPAL","identifier":"OPTSTKCOLPAL28-10-2025CE2120.00","openInterest":0,"changeinOpenInterest":0,"pchangeinOpenInterest":0,"totalTradedVolume":0,"impliedVolatility":0,"lastPrice":0,"change":0,"totalBuyQuantity":6525,"totalSellQuantity":3150,"buyPrice1":225.55,"buyQuantity1":900,"sellPrice1":310.25,"sellQuantity1":900,"underlyingValue":2328.6,"optionType":null,"pchange":0},"PE":{"strikePrice":2120,"expiryDate":"28-10-2025","underlying":"COLPAL","identifier":"OPTSTKCOLPAL28-10-2025PE2120.00","openInterest":0,"changeinOpenInterest":0,"pchangeinOpenInterest":0,"totalTradedVolume":0,"impliedVolatility":0,"lastPrice":0,"change":0,"totalBuyQuantity":0,"totalSellQuantity":0,"buyPrice1":0,"buyQuantity1":0,"sellPrice1":0,"sellQuantity1":0,"underlyingValue":2328.6,"optionType":null,"pchange":0},"strikePrice":2120},{"expiryDates":"28-Oct-2025","CE":{"strikePrice":2160,"expiryDate":"28-10-2025","underlying":"COLPAL","identifier":"OPTSTKCOLPAL28-10-2025CE2160.00","openInterest":0,"changeinOpenInterest":0,"pchangeinOpenInterest":0,"totalTradedVolume":0,"impliedVolatility":0,"lastPrice":0,"change":0,"totalBuyQuantity":6525,"totalSellQuantity":3150,"buyPrice1":186.05,"buyQuantity1":900,"sellPrice1":270.75,"sellQuantity1":900,"underlyingValue":2328.6,"optionType":null,"pchange":0},"PE":{"strikePrice":2160,"expiryDate":"28-10-2025","underlying":"COLPAL","identifier":"OPTSTKCOLPAL28-10-2025PE2160.00","openInterest":0,"changeinOpenInterest":0,"pchangeinOpenInterest":0,"totalTradedVolume":0,"impliedVolatility":0,"lastPrice":0,"change":0,"totalBuyQuantity":0,"totalSellQuantity":6525,"buyPrice1":0,"buyQuantity1":0,"sellPrice1":68.25,"sellQuantity1":900,"underlyingValue":2328.6,"optionType":null,"pchange":0},"strikePrice":2160},{"expiryDates":"28-Oct-2025","CE":{"strikePrice":2200,"expiryDate":"28-10-2025","underlying":"COLPAL","identifier":"OPTSTKCOLPAL28-10-2025CE2200.00","openInterest":0,"changeinOpenInterest":0,"pchangeinOpenInterest":0,"totalTradedVolume":0,"impliedVolatility":0,"lastPrice":0,"change":0,"totalBuyQuantity":6525,"totalSellQuantity":900,"buyPrice1":147.55,"buyQuantity1":900,"sellPrice1":228.55,"sellQuantity1":900,"underlyingValue":2328.6,"optionType":null,"pchange":0},"PE":{"strikePrice":2200,"expiryDate":"28-10-2025","underlying":"COLPAL","identifier":"OPTSTKCOLPAL28-10-2025PE2200.00","openInterest":0,"changeinOpenInterest":0,"pchangeinOpenInterest":0,"totalTradedVolume":0,"impliedVolatility":0,"lastPrice":0,"change":0,"totalBuyQuantity":450,"totalSellQuantity":6525,"buyPrice1":15.05,"buyQuantity1":450,"sellPrice1":68.6,"sellQuantity1":900,"underlyingValue":2328.6,"optionType":null,"pchange":0},"strikePrice":2200},{"expiryDates":"28-Oct-2025","CE":{"strikePrice":2240,"expiryDate":"28-10-2025","underlying":"COLPAL","identifier":"OPTSTKCOLPAL28-10-2025CE2240.00","openInterest":0,"changeinOpenInterest":0,"pchangeinOpenInterest":0,"totalTradedVolume":0,"impliedVolatility":0,"lastPrice":0,"change":0,"totalBuyQuantity":6525,"totalSellQuantity":3150,"buyPrice1":107.65,"buyQuantity1":900,"sellPrice1":189.55,"sellQuantity1":900,"underlyingValue":2328.6,"optionType":null,"pchange":0},"PE":{"strikePrice":2240,"expiryDate":"28-10-2025","underlying":"COLPAL","identifier":"OPTSTKCOLPAL28-10-2025PE2240.00","openInterest":0,"changeinOpenInterest":0,"pchangeinOpenInterest":0,"totalTradedVolume":0,"impliedVolatility":0,"lastPrice":0,"change":0,"totalBuyQuantity":0,"totalSellQuantity":6750,"buyPrice1":0,"buyQuantity1":0,"sellPrice1":60,"sellQuantity1":225,"underlyingValue":2328.6,"optionType":null,"pchange":0},"strikePrice":2240},{"expiryDates":"28-Oct-2025","CE":{"strikePrice":2280,"expiryDate":"28-10-2025","underlying":"COLPAL","identifier":"OPTSTKCOLPAL28-10-2025CE2280.00","openInterest":0,"changeinOpenInterest":0,"pchangeinOpenInterest":0,"totalTradedVolume":0,"impliedVolatility":0,"lastPrice":0,"change":0,"totalBuyQuantity":6525,"totalSellQuantity":6525,"buyPrice1":67.55,"buyQuantity1":900,"sellPrice1":161.6,"sellQuantity1":1125,"underlyingValue":2328.6,"optionType":null,"pchange":0},"PE":{"strikePrice":2280,"expiryDate":"28-10-2025","underlying":"COLPAL","identifier":"OPTSTKCOLPAL28-10-2025PE2280.00","openInterest":0,"changeinOpenInterest":0,"pchangeinOpenInterest":0,"totalTradedVolume":0,"impliedVolatility":0,"lastPrice":0,"change":0,"totalBuyQuantity":225,"totalSellQuantity":6525,"buyPrice1":35.05,"buyQuantity1":225,"sellPrice1":76.45,"sellQuantity1":900,"underlyingValue":2328.6,"optionType":null,"pchange":0},"strikePrice":2280},{"expiryDates":"28-Oct-2025","CE":{"strikePrice":2300,"expiryDate":"28-10-2025","underlying":"COLPAL","identifier":"OPTSTKCOLPAL28-10-2025CE2300.00","openInterest":0,"changeinOpenInterest":0,"pchangeinOpenInterest":0,"totalTradedVolume":0,"impliedVolatility":0,"lastPrice":0,"change":0,"totalBuyQuantity":0,"totalSellQuantity":0,"buyPrice1":0,"buyQuantity1":0,"sellPrice1":0,"sellQuantity1":0,"underlyingValue":2328.6,"optionType":null,"pchange":0},"PE":{"strikePrice":2300,"expiryDate":"28-10-2025","underlying":"COLPAL","identifier":"OPTSTKCOLPAL28-10-2025PE2300.00","openInterest":0,"changeinOpenInterest":0,"pchangeinOpenInterest":0,"totalTradedVolume":0,"impliedVolatility":0,"lastPrice":0,"change":0,"totalBuyQuantity":225,"totalSellQuantity":450,"buyPrice1":39.15,"buyQuantity1":225,"sellPrice1":67.95,"sellQuantity1":225,"underlyingValue":2328.6,"optionType":null,"pchange":0},"strikePrice":2300},{"expiryDates":"28-Oct-2025","CE":{"strikePrice":2320,"expiryDate":"28-10-2025","underlying":"COLPAL","identifier":"OPTSTKCOLPAL28-10-2025CE2320.00","openInterest":0,"changeinOpenInterest":0,"pchangeinOpenInterest":0,"totalTradedVolume":0,"impliedVolatility":0,"lastPrice":0,"change":0,"totalBuyQuantity":0,"totalSellQuantity":6750,"buyPrice1":0,"buyQuantity1":0,"sellPrice1":160.1,"sellQuantity1":225,"underlyingValue":2328.6,"optionType":null,"pchange":0},"PE":{"strikePrice":2320,"expiryDate":"28-10-2025","underlying":"COLPAL","identifier":"OPTSTKCOLPAL28-10-2025PE2320.00","openInterest":0,"changeinOpenInterest":0,"pchangeinOpenInterest":0,"totalTradedVolume":0,"impliedVolatility":0,"lastPrice":0,"change":0,"totalBuyQuantity":225,"totalSellQuantity":6525,"buyPrice1":46.65,"buyQuantity1":225,"sellPrice1":134.1,"sellQuantity1":900,"underlyingValue":2328.6,"optionType":null,"pchange":0},"strikePrice":2320},{"expiryDates":"28-Oct-2025","CE":{"strikePrice":2340,"expiryDate":"28-10-2025","underlying":"COLPAL","identifier":"OPTSTKCOLPAL28-10-2025CE2340.00","openInterest":0,"changeinOpenInterest":0,"pchangeinOpenInterest":0,"totalTradedVolume":0,"impliedVolatility":0,"lastPrice":0,"change":0,"totalBuyQuantity":0,"totalSellQuantity":225,"buyPrice1":0,"buyQuantity1":0,"sellPrice1":123.15,"sellQuantity1":225,"underlyingValue":2328.6,"optionType":null,"pchange":0},"PE":{"strikePrice":0,"expiryDate":null,"underlying":null,"identifier":null,"openInterest":0,"changeinOpenInterest":0,"pchangeinOpenInterest":0,"totalTradedVolume":0,"impliedVolatility":0,"lastPrice":0,"change":0,"totalBuyQuantity":0,"totalSellQuantity":0,"buyPrice1":0,"buyQuantity1":0,"sellPrice1":0,"sellQuantity1":0,"underlyingValue":0,"optionType":null,"pchange":0},"strikePrice":2340},{"expiryDates":"28-Oct-2025","CE":{"strikePrice":2360,"expiryDate":"28-10-2025","underlying":"COLPAL","identifier":"OPTSTKCOLPAL28-10-2025CE2360.00","openInterest":0,"changeinOpenInterest":0,"pchangeinOpenInterest":0,"totalTradedVolume":0,"impliedVolatility":0,"lastPrice":0,"change":0,"totalBuyQuantity":0,"totalSellQuantity":3375,"buyPrice1":0,"buyQuantity1":0,"sellPrice1":109.65,"sellQuantity1":225,"underlyingValue":2328.6,"optionType":null,"pchange":0},"PE":{"strikePrice":2360,"expiryDate":"28-10-2025","underlying":"COLPAL","identifier":"OPTSTKCOLPAL28-10-2025PE2360.00","openInterest":0,"changeinOpenInterest":0,"pchangeinOpenInterest":0,"totalTradedVolume":0,"impliedVolatility":0,"lastPrice":0,"change":0,"totalBuyQuantity":0,"totalSellQuantity":6525,"buyPrice1":0,"buyQuantity1":0,"sellPrice1":134.05,"sellQuantity1":900,"underlyingValue":2328.6,"optionType":null,"pchange":0},"strikePrice":2360},{"expiryDates":"28-Oct-2025","CE":{"strikePrice":2380,"expiryDate":"28-10-2025","underlying":"COLPAL","identifier":"OPTSTKCOLPAL28-10-2025CE2380.00","openInterest":0,"changeinOpenInterest":0,"pchangeinOpenInterest":0,"totalTradedVolume":0,"impliedVolatility":0,"lastPrice":0,"change":0,"totalBuyQuantity":0,"totalSellQuantity":225,"buyPrice1":0,"buyQuantity1":0,"sellPrice1":103.95,"sellQuantity1":225,"underlyingValue":2328.6,"optionType":null,"pchange":0},"PE":{"strikePrice":0,"expiryDate":null,"underlying":null,"identifier":null,"openInterest":0,"changeinOpenInterest":0,"pchangeinOpenInterest":0,"totalTradedVolume":0,"impliedVolatility":0,"lastPrice":0,"change":0,"totalBuyQuantity":0,"totalSellQuantity":0,"buyPrice1":0,"buyQuantity1":0,"sellPrice1":0,"sellQuantity1":0,"underlyingValue":0,"optionType":null,"pchange":0},"strikePrice":2380},{"expiryDates":"28-Oct-2025","CE":{"strikePrice":2400,"expiryDate":"28-10-2025","underlying":"COLPAL","identifier":"OPTSTKCOLPAL28-10-2025CE2400.00","openInterest":2,"changeinOpenInterest":2,"pchangeinOpenInterest":0,"totalTradedVolume":3,"impliedVolatility":21.97,"lastPrice":68.15,"change":-11.85,"totalBuyQuantity":225,"totalSellQuantity":7425,"buyPrice1":25,"buyQuantity1":225,"sellPrice1":70.7,"sellQuantity1":225,"underlyingValue":2328.6,"optionType":null,"pchange":-14.8125},"PE":{"strikePrice":2400,"expiryDate":"28-10-2025","underlying":"COLPAL","identifier":"OPTSTKCOLPAL28-10-2025PE2400.00","openInterest":0,"changeinOpenInterest":0,"pchangeinOpenInterest":0,"totalTradedVolume":0,"impliedVolatility":0,"lastPrice":0,"change":0,"totalBuyQuantity":0,"totalSellQuantity":6525,"buyPrice1":0,"buyQuantity1":0,"sellPrice1":125.85,"sellQuantity1":2250,"underlyingValue":2328.6,"optionType":null,"pchange":0},"strikePrice":2400},{"expiryDates":"28-Oct-2025","CE":{"strikePrice":2420,"expiryDate":"28-10-2025","underlying":"COLPAL","identifier":"OPTSTKCOLPAL28-10-2025CE2420.00","openInterest":0,"changeinOpenInterest":0,"pchangeinOpenInterest":0,"totalTradedVolume":0,"impliedVolatility":0,"lastPrice":0,"change":0,"totalBuyQuantity":0,"totalSellQuantity":225,"buyPrice1":0,"buyQuantity1":0,"sellPrice1":82.85,"sellQuantity1":225,"underlyingValue":2328.6,"optionType":null,"pchange":0},"PE":{"strikePrice":0,"expiryDate":null,"underlying":null,"identifier":null,"openInterest":0,"changeinOpenInterest":0,"pchangeinOpenInterest":0,"totalTradedVolume":0,"impliedVolatility":0,"lastPrice":0,"change":0,"totalBuyQuantity":0,"totalSellQuantity":0,"buyPrice1":0,"buyQuantity1":0,"sellPrice1":0,"sellQuantity1":0,"underlyingValue":0,"optionType":null,"pchange":0},"strikePrice":2420},{"expiryDates":"28-Oct-2025","CE":{"strikePrice":2440,"expiryDate":"28-10-2025","underlying":"COLPAL","identifier":"OPTSTKCOLPAL28-10-2025CE2440.00","openInterest":0,"changeinOpenInterest":0,"pchangeinOpenInterest":0,"totalTradedVolume":0,"impliedVolatility":0,"lastPrice":0,"change":0,"totalBuyQuantity":0,"totalSellQuantity":6750,"buyPrice1":0,"buyQuantity1":0,"sellPrice1":75.05,"sellQuantity1":225,"underlyingValue":2328.6,"optionType":null,"pchange":0},"PE":{"strikePrice":2440,"expiryDate":"28-10-2025","underlying":"COLPAL","identifier":"OPTSTKCOLPAL28-10-2025PE2440.00","openInterest":0,"changeinOpenInterest":0,"pchangeinOpenInterest":0,"totalTradedVolume":0,"impliedVolatility":0,"lastPrice":0,"change":0,"totalBuyQuantity":0,"totalSellQuantity":6525,"buyPrice1":0,"buyQuantity1":0,"sellPrice1":171.4,"sellQuantity1":900,"underlyingValue":2328.6,"optionType":null,"pchange":0},"strikePrice":2440},{"expiryDates":"28-Oct-2025","CE":{"strikePrice":2460,"expiryDate":"28-10-2025","underlying":"COLPAL","identifier":"OPTSTKCOLPAL28-10-2025CE2460.00","openInterest":0,"changeinOpenInterest":0,"pchangeinOpenInterest":0,"totalTradedVolume":0,"impliedVolatility":0,"lastPrice":0,"change":0,"totalBuyQuantity":0,"totalSellQuantity":225,"buyPrice1":0,"buyQuantity1":0,"sellPrice1":71.55,"sellQuantity1":225,"underlyingValue":2328.6,"optionType":null,"pchange":0},"PE":{"strikePrice":0,"expiryDate":null,"underlying":null,"identifier":null,"openInterest":0,"changeinOpenInterest":0,"pchangeinOpenInterest":0,"totalTradedVolume":0,"impliedVolatility":0,"lastPrice":0,"change":0,"totalBuyQuantity":0,"totalSellQuantity":0,"buyPrice1":0,"buyQuantity1":0,"sellPrice1":0,"sellQuantity1":0,"underlyingValue":0,"optionType":null,"pchange":0},"strikePrice":2460},{"expiryDates":"28-Oct-2025","CE":{"strikePrice":2480,"expiryDate":"28-10-2025","underlying":"COLPAL","identifier":"OPTSTKCOLPAL28-10-2025CE2480.00","openInterest":0,"changeinOpenInterest":0,"pchangeinOpenInterest":0,"totalTradedVolume":0,"impliedVolatility":0,"lastPrice":0,"change":0,"totalBuyQuantity":0,"totalSellQuantity":3375,"buyPrice1":0,"buyQuantity1":0,"sellPrice1":68.4,"sellQuantity1":225,"underlyingValue":2328.6,"optionType":null,"pchange":0},"PE":{"strikePrice":2480,"expiryDate":"28-10-2025","underlying":"COLPAL","identifier":"OPTSTKCOLPAL28-10-2025PE2480.00","openInterest":0,"changeinOpenInterest":0,"pchangeinOpenInterest":0,"totalTradedVolume":0,"impliedVolatility":0,"lastPrice":0,"change":0,"totalBuyQuantity":3150,"totalSellQuantity":6525,"buyPrice1":106.15,"buyQuantity1":900,"sellPrice1":213.5,"sellQuantity1":2250,"underlyingValue":2328.6,"optionType":null,"pchange":0},"strikePrice":2480},{"expiryDates":"28-Oct-2025","CE":{"strikePrice":2500,"expiryDate":"28-10-2025","underlying":"COLPAL","identifier":"OPTSTKCOLPAL28-10-2025CE2500.00","openInterest":0,"changeinOpenInterest":0,"pchangeinOpenInterest":0,"totalTradedVolume":0,"impliedVolatility":0,"lastPrice":0,"change":0,"totalBuyQuantity":225,"totalSellQuantity":225,"buyPrice1":12,"buyQuantity1":225,"sellPrice1":65.25,"sellQuantity1":225,"underlyingValue":2328.6,"optionType":null,"pchange":0},"PE":{"strikePrice":0,"expiryDate":null,"underlying":null,"identifier":null,"openInterest":0,"changeinOpenInterest":0,"pchangeinOpenInterest":0,"totalTradedVolume":0,"impliedVolatility":0,"lastPrice":0,"change":0,"totalBuyQuantity":0,"totalSellQuantity":0,"buyPrice1":0,"buyQuantity1":0,"sellPrice1":0,"sellQuantity1":0,"underlyingValue":0,"optionType":null,"pchange":0},"strikePrice":2500},{"expiryDates":"28-Oct-2025","CE":{"strikePrice":2520,"expiryDate":"28-10-2025","underlying":"COLPAL","identifier":"OPTSTKCOLPAL28-10-2025CE2520.00","openInterest":0,"changeinOpenInterest":0,"pchangeinOpenInterest":0,"totalTradedVolume":0,"impliedVolatility":0,"lastPrice":0,"change":0,"totalBuyQuantity":0,"totalSellQuantity":3375,"buyPrice1":0,"buyQuantity1":0,"sellPrice1":73.75,"sellQuantity1":225,"underlyingValue":2328.6,"optionType":null,"pchange":0},"PE":{"strikePrice":2520,"expiryDate":"28-10-2025","underlying":"COLPAL","identifier":"OPTSTKCOLPAL28-10-2025PE2520.00","openInterest":0,"changeinOpenInterest":0,"pchangeinOpenInterest":0,"totalTradedVolume":0,"impliedVolatility":0,"lastPrice":0,"change":0,"totalBuyQuantity":3150,"totalSellQuantity":6525,"buyPrice1":144.8,"buyQuantity1":900,"sellPrice1":246.65,"sellQuantity1":900,"underlyingValue":2328.6,"optionType":null,"pchange":0},"strikePrice":2520},{"expiryDates":"28-Oct-2025","CE":{"strikePrice":2560,"expiryDate":"28-10-2025","underlying":"COLPAL","identifier":"OPTSTKCOLPAL28-10-2025CE2560.00","openInterest":0,"changeinOpenInterest":0,"pchangeinOpenInterest":0,"totalTradedVolume":0,"impliedVolatility":0,"lastPrice":0,"change":0,"totalBuyQuantity":0,"totalSellQuantity":225,"buyPrice1":0,"buyQuantity1":0,"sellPrice1":65.75,"sellQuantity1":225,"underlyingValue":2328.6,"optionType":null,"pchange":0},"PE":{"strikePrice":2560,"expiryDate":"28-10-2025","underlying":"COLPAL","identifier":"OPTSTKCOLPAL28-10-2025PE2560.00","openInterest":0,"changeinOpenInterest":0,"pchangeinOpenInterest":0,"totalTradedVolume":0,"impliedVolatility":0,"lastPrice":0,"change":0,"totalBuyQuantity":3150,"totalSellQuantity":6525,"buyPrice1":184.3,"buyQuantity1":900,"sellPrice1":286.45,"sellQuantity1":900,"underlyingValue":2328.6,"optionType":null,"pchange":0},"strikePrice":2560},{"expiryDates":"28-Oct-2025","CE":{"strikePrice":2600,"expiryDate":"28-10-2025","underlying":"COLPAL","identifier":"OPTSTKCOLPAL28-10-2025CE2600.00","openInterest":0,"changeinOpenInterest":0,"pchangeinOpenInterest":0,"totalTradedVolume":0,"impliedVolatility":0,"lastPrice":0,"change":0,"totalBuyQuantity":18450,"totalSellQuantity":0,"buyPrice1":0.5,"buyQuantity1":1350,"sellPrice1":0,"sellQuantity1":0,"underlyingValue":2328.6,"optionType":null,"pchange":0},"PE":{"strikePrice":0,"expiryDate":null,"underlying":null,"identifier":null,"openInterest":0,"changeinOpenInterest":0,"pchangeinOpenInterest":0,"totalTradedVolume":0,"impliedVolatility":0,"lastPrice":0,"change":0,"totalBuyQuantity":0,"totalSellQuantity":0,"buyPrice1":0,"buyQuantity1":0,"sellPrice1":0,"sellQuantity1":0,"underlyingValue":0,"optionType":null,"pchange":0},"strikePrice":2600},{"expiryDates":"28-Oct-2025","CE":{"strikePrice":2640,"expiryDate":"28-10-2025","underlying":"COLPAL","identifier":"OPTSTKCOLPAL28-10-2025CE2640.00","openInterest":0,"changeinOpenInterest":0,"pchangeinOpenInterest":0,"totalTradedVolume":0,"impliedVolatility":0,"lastPrice":0,"change":0,"totalBuyQuantity":17100,"totalSellQuantity":0,"buyPrice1":0.1,"buyQuantity1":17100,"sellPrice1":0,"sellQuantity1":0,"underlyingValue":2328.6,"optionType":null,"pchange":0},"PE":{"strikePrice":0,"expiryDate":null,"underlying":null,"identifier":null,"openInterest":0,"changeinOpenInterest":0,"pchangeinOpenInterest":0,"totalTradedVolume":0,"impliedVolatility":0,"lastPrice":0,"change":0,"totalBuyQuantity":0,"totalSellQuantity":0,"buyPrice1":0,"buyQuantity1":0,"sellPrice1":0,"sellQuantity1":0,"underlyingValue":0,"optionType":null,"pchange":0},"strikePrice":2640}],"CE":{"totOI":2,"totVol":3},"PE":{"totOI":0,"totVol":0}}}